preprocessing_tools/__init__.py
preprocessing_tools/_utils.py
preprocessing_tools/binning.py
preprocessing_tools/dataEncoding.py
preprocessing_tools/data_cleaner.py
preprocessing_tools/handling_outliers.py
preprocessing_tools/interaction_features.py
preprocessing_tools/polynomial_features.py
preprocessing_tools/scaler.py
preprocessing_tools/transform.py
preprocessing_tools-0.0.2.dist-info/METADATA
preprocessing_tools-0.0.2.dist-info/WHEEL
preprocessing_tools-0.0.2.dist-info/top_level.txt
preprocessing_tools-0.0.2.dist-info/RECORD
